<ValueSet xmlns="http://hl7.org/fhir">
    <id value="nicer-aprefixptnm"/>
    <url value="http://fhir.ch/ig/ch-crl/ValueSet/nicer-aprefixptnm"/>
    <version value="0.0.1"/>
    <name value="NiceraPrefixpTNM"/>
    <title value="Nicer a-Prefix pTNM"/>
    <status value="draft"/>
    <experimental value="false"/>
    <date value="2019-09-02"/>
    <publisher value="Bundesamt für Gesundheit BAG"/>
    <description value="The prefix a indicates that classification is first determined at autopsy." />
    <compose>
        <include>
            <system value="http://fhir.ch/ig/ch-crl/CodeSystem/nicer-aprefixptnm"/>
        </include>
    </compose>
</ValueSet>